chessAnalyzer/__init__.py
chessAnalyzer/chess_graph.py
chessAnalyzer/main.py
chessAnalyzer/Chess-Coordinate-Trainer-master/__init__.py
chessAnalyzer/Chess-Coordinate-Trainer-master/chess_coordinate_trainer.py
chessAnalyzer/Engine/__init__.py
chessAnalyzer/eco_codes/__init__.py
chessAnalyzer-0.1.0.dist-info/LICENSE
chessAnalyzer-0.1.0.dist-info/METADATA
chessAnalyzer-0.1.0.dist-info/WHEEL
chessAnalyzer-0.1.0.dist-info/top_level.txt
chessAnalyzer-0.1.0.dist-info/RECORD
