Metadata-Version: 2.1
Name: chessAnalyzer
Version: 0.1.0
Summary: Analyses games and positions. Possible to have a Game Report similar to the one from chess.com, including graphs.
Home-page: https://github.com/CoderAryanAnand/pythonChessAnalyzer
Author: Aryan Anand
Author-email: aryananand.chess@gmail.com
License: UNKNOWN
Platform: UNKNOWN
Classifier: Programming Language :: Python :: 3
Classifier: License :: OSI Approved :: MIT License
Classifier: Operating System :: OS Independent
Requires-Python: >=3.6
